wnastart/__init__.py
wnastart/wnastart.py
wnastart-0.1.dist-info/METADATA
wnastart-0.1.dist-info/WHEEL
wnastart-0.1.dist-info/entry_points.txt
wnastart-0.1.dist-info/top_level.txt
wnastart-0.1.dist-info/RECORD
